plxcontroller/__init__.py
plxcontroller/globals.py
plxcontroller/plaxis_2d_input_controller.py
plxcontroller/plaxis_2d_output_controller.py
plxcontroller/plaxis_3d_input_controller.py
plxcontroller/plaxis_3d_output_controller.py
plxcontroller/geometry_3d/__init__.py
plxcontroller/geometry_3d/bounding_box_3d.py
plxcontroller/geometry_3d/convex_hull_3d.py
plxcontroller/geometry_3d/operations_3d.py
plxcontroller/geometry_3d/point_3d.py
plxcontroller/geometry_3d/polygon_3d.py
plxcontroller/mesh_3d/__init__.py
plxcontroller/mesh_3d/node_3d.py
plxcontroller-0.8.1.dist-info/LICENSE
plxcontroller-0.8.1.dist-info/METADATA
plxcontroller-0.8.1.dist-info/WHEEL
plxcontroller-0.8.1.dist-info/top_level.txt
plxcontroller-0.8.1.dist-info/RECORD
