Metadata-Version: 2.1
Name: plxcontroller
Version: 0.8.1
Summary: Controllers to create and modify Plaxis 2D and 3D models with enhanced functionalities.
License: MIT License
Project-URL: repository, https://github.com/cemsbv/plxcontroller
Keywords: plxcontroller,CEMS,PLAXIS automation
Requires-Python: >=3.9
License-File: LICENSE
Requires-Dist: plxscripting <2.0.0,>=1.0.4
Requires-Dist: numpy <2.0,>=1.24.2
Requires-Dist: shapely <3.0,>=2.0.1
Requires-Dist: matplotlib ==3.7.1
Requires-Dist: scikit-spatial <8.0.0,>=7.0.0
Provides-Extra: lint
Requires-Dist: mypy ==1.6.1 ; extra == 'lint'
Requires-Dist: mypy-extensions ==1.0.0 ; extra == 'lint'
Requires-Dist: tomli ==2.0.1 ; extra == 'lint'
Requires-Dist: typing-extensions ==4.7.1 ; extra == 'lint'
Requires-Dist: black[jupyter] ==23.10.1 ; extra == 'lint'
Requires-Dist: click ==8.1.3 ; extra == 'lint'
Requires-Dist: packaging ==23.2 ; extra == 'lint'
Requires-Dist: pathspec ==0.11.1 ; extra == 'lint'
Requires-Dist: platformdirs ==3.5.1 ; extra == 'lint'
Requires-Dist: isort ==5.12.0 ; extra == 'lint'
Requires-Dist: flake8 ==6.0.0 ; extra == 'lint'
Requires-Dist: mccabe ==0.7.0 ; extra == 'lint'
Requires-Dist: pycodestyle ==2.10.0 ; extra == 'lint'
Requires-Dist: pyflakes ==3.0.1 ; extra == 'lint'
Requires-Dist: pandas-stubs <3,>2 ; extra == 'lint'
Requires-Dist: types-tqdm <5,>4 ; extra == 'lint'
Provides-Extra: test
Requires-Dist: coveralls ; extra == 'test'
Requires-Dist: pytest ; extra == 'test'
